speechkit/__init__.py
speechkit/_auth.py
speechkit/_synthesis.py
speechkit/auth.py
speechkit/exceptions.py
speechkit/utils.py
speechkit/_recognition/__init__.py
speechkit/_recognition/streaming_recognition.py
speechkit/_recognition/sync_recognition.py
speechkit/_recognition/google/__init__.py
speechkit/_recognition/google/api/__init__.py
speechkit/_recognition/google/api/annotations_pb2.py
speechkit/_recognition/google/api/annotations_pb2_grpc.py
speechkit/_recognition/google/api/http_pb2.py
speechkit/_recognition/google/api/http_pb2_grpc.py
speechkit/_recognition/google/rpc/__init__.py
speechkit/_recognition/google/rpc/status_pb2.py
speechkit/_recognition/google/rpc/status_pb2_grpc.py
speechkit/_recognition/yandex/__init__.py
speechkit/_recognition/yandex/cloud/__init__.py
speechkit/_recognition/yandex/cloud/ai/__init__.py
speechkit/_recognition/yandex/cloud/ai/stt/__init__.py
speechkit/_recognition/yandex/cloud/ai/stt/v2/__init__.py
speechkit/_recognition/yandex/cloud/ai/stt/v2/stt_service_pb2.py
speechkit/_recognition/yandex/cloud/ai/stt/v2/stt_service_pb2_grpc.py
speechkit/_recognition/yandex/cloud/api/__init__.py
speechkit/_recognition/yandex/cloud/api/operation_pb2.py
speechkit/_recognition/yandex/cloud/api/operation_pb2_grpc.py
speechkit/_recognition/yandex/cloud/operation/__init__.py
speechkit/_recognition/yandex/cloud/operation/operation_pb2.py
speechkit/_recognition/yandex/cloud/operation/operation_pb2_grpc.py
tests/__init__.py
tests/test_auth.py
tests/test_exceptions.py
tests/test_long_audio_recognition.py
tests/test_short_audio_recognition.py
tests/test_speech_synthesis.py
tests/test_streaming_recognition.py
tests/test_utils.py
speechkit-2.2.3.dist-info/LICENSE.txt
speechkit-2.2.3.dist-info/METADATA
speechkit-2.2.3.dist-info/WHEEL
speechkit-2.2.3.dist-info/top_level.txt
speechkit-2.2.3.dist-info/RECORD
