Metadata-Version: 2.2
Name: speechkit
Version: 2.2.3
Summary: Python SDK for Yandex Speechkit API.
Home-page: https://github.com/TikhonP/yandex-speechkit-lib-python
Author: Tikhon Petrishchev
Author-email: tikhon.petrishchev@gmail.com
Project-URL: Bug Tracker, https://github.com/TikhonP/yandex-speechkit-lib-python/issues
Project-URL: Documentation, https://yandex-speechkit-lib-python.readthedocs.io/en/latest/index.html
Project-URL: GitHub, https://github.com/TikhonP/yandex-speechkit-lib-python
Classifier: Development Status :: 5 - Production/Stable
Classifier: Intended Audience :: Developers
Classifier: Natural Language :: English
Classifier: Programming Language :: Python
Classifier: Programming Language :: Python :: 3
Classifier: Programming Language :: Python :: 3.6
Classifier: Programming Language :: Python :: 3.7
Classifier: Programming Language :: Python :: 3.8
Classifier: Programming Language :: Python :: 3.9
Classifier: Programming Language :: Python :: 3.10
Classifier: License :: OSI Approved :: MIT License
Classifier: Operating System :: OS Independent
Requires-Python: >=3.6
License-File: LICENSE.txt
Requires-Dist: boto3
Requires-Dist: requests
Requires-Dist: grpcio-tools>=1.39.0
Requires-Dist: protobuf~=3.19.6
Requires-Dist: pyjwt>=2.1.0
Requires-Dist: cryptography
